snetx/__init__.py
snetx/utils.py
snetx/cuend/__init__.py
snetx/cuend/neuron.py
snetx/cuend/nnfunc.py
snetx/cuend/utils.py
snetx/cuend/C/neuron.cu
snetx/cuend/C/surrogate.in
snetx/dataset/__init__.py
snetx/dataset/vision.py
snetx/dataset/ddp/__init__.py
snetx/dataset/ddp/vision.py
snetx/models/__init__.py
snetx/models/svggnet.py
snetx/snn/__init__.py
snetx/snn/algorithm.py
snetx/snn/neuron.py
snetx-0.1.3.dist-info/LICENSE
snetx-0.1.3.dist-info/METADATA
snetx-0.1.3.dist-info/WHEEL
snetx-0.1.3.dist-info/top_level.txt
snetx-0.1.3.dist-info/RECORD
