Metadata-Version: 2.1
Name: snetx
Version: 0.1.3
Summary: Package for quickly building spiking neural network.
Author-email: Lang Xue <202221080723@std.uestc.edu.cn>
Maintainer-email: Lang Xue <202221080723@std.uestc.edu.cn>
License: Copyright (c) 2023 Lang Xue
Project-URL: Homepage, https://github.com/1xueLang/snetx
Project-URL: Documentation, https://github.com/1xueLang/snetx/blob/0.1.3/readme.md
Project-URL: Repository, https://github.com/1xueLang/snetx.git
Project-URL: Bug Tracker, https://github.com/1xueLang/snetx/issues
Classifier: Programming Language :: Python :: 3
Classifier: License :: OSI Approved :: MIT License
Classifier: Operating System :: OS Independent
Requires-Python: >=3.6
License-File: LICENSE
Requires-Dist: termcolor
